ansible_vault_rekey/__init__.py
ansible_vault_rekey/ansible_vault_rekey.py
ansible_vault_rekey/cli.py
ansible_vault_rekey/vaultstring.py
ansible_vault_rekey-2.0.1.dist-info/AUTHORS.rst
ansible_vault_rekey-2.0.1.dist-info/LICENSE
ansible_vault_rekey-2.0.1.dist-info/METADATA
ansible_vault_rekey-2.0.1.dist-info/WHEEL
ansible_vault_rekey-2.0.1.dist-info/entry_points.txt
ansible_vault_rekey-2.0.1.dist-info/top_level.txt
ansible_vault_rekey-2.0.1.dist-info/RECORD
