Metadata-Version: 2.1
Name: ansible-vault-rekey
Version: 2.0.1
Summary: Roll keys and re-encrypt secrets in any repo using Ansible Vault
Home-page: https://github.com/inhumantsar/python-ansible-vault-rekey
Author: Shaun Martin
Author-email: shaun@samsite.ca
License: BSD license
Keywords: ansible-vault-rekey
Platform: UNKNOWN
Classifier: Development Status :: 2 - Pre-Alpha
Classifier: Intended Audience :: Developers
Classifier: License :: OSI Approved :: BSD License
Classifier: Natural Language :: English
Classifier: Programming Language :: Python :: 3
Classifier: Programming Language :: Python :: 3.6
Classifier: Programming Language :: Python :: 3.7
Classifier: Programming Language :: Python :: 3.8
Classifier: Programming Language :: Python :: 3.9
Requires-Dist: click (~=7.1.2)
Requires-Dist: ansible (~=2.9.10)
